{
  "date": "2026-07-16",
  "generated_at": "2026-07-16T19:21:28+09:00",
  "picked_code": "004310",
  "stocks": [
    {
      "code": "004310",
      "name": "현대약품",
      "pm320_pick": {
        "is_pick": true,
        "pick_date": "2026-07-16",
        "entry_price": 7600,
        "watering_target_price": 7114,
        "watering_weight": "첫 매수와 동일 수량(1배)",
        "take_profit_target_price": 7843,
        "take_profit_after_watering_price": 7592,
        "expiry_date": "2026-07-21",
        "current_state": "running",
        "current_pnl_pct": 0.0,
        "current_mdd_pct": 0.0,
        "current_mdd_peak_pct": 0.0,
        "d_offset": 0,
        "result": null
      }
    },
    {
      "code": "006660",
      "name": "삼성공조",
      "pm320_pick": {
        "is_pick": false,
        "pick_date": "2026-07-16",
        "entry_price": 13580,
        "watering_target_price": 12711,
        "watering_weight": "첫 매수와 동일 수량(1배)",
        "take_profit_target_price": 14015,
        "take_profit_after_watering_price": 13566,
        "expiry_date": "2026-07-21",
        "current_state": "running",
        "current_pnl_pct": 0.0,
        "current_mdd_pct": 0.0,
        "current_mdd_peak_pct": 0.0,
        "d_offset": 0,
        "result": null
      }
    },
    {
      "code": "005360",
      "name": "모나미",
      "pm320_pick": {
        "is_pick": false,
        "pick_date": "2026-07-16",
        "entry_price": 3730,
        "watering_target_price": 3491,
        "watering_weight": "첫 매수와 동일 수량(1배)",
        "take_profit_target_price": 3849,
        "take_profit_after_watering_price": 3726,
        "expiry_date": "2026-07-21",
        "current_state": "running",
        "current_pnl_pct": 0.0,
        "current_mdd_pct": 0.0,
        "current_mdd_peak_pct": 0.0,
        "d_offset": 0,
        "result": null
      }
    },
    {
      "code": "049080",
      "name": "기가레인",
      "pm320_pick": {
        "is_pick": false,
        "pick_date": "2026-07-16",
        "entry_price": 11290,
        "watering_target_price": 10567,
        "watering_weight": "첫 매수와 동일 수량(1배)",
        "take_profit_target_price": 11651,
        "take_profit_after_watering_price": 11278,
        "expiry_date": "2026-07-21",
        "current_state": "running",
        "current_pnl_pct": 0.0,
        "current_mdd_pct": 0.0,
        "current_mdd_peak_pct": 0.0,
        "d_offset": 0,
        "result": null
      }
    },
    {
      "code": "279570",
      "name": "케이뱅크",
      "pm320_pick": {
        "is_pick": false,
        "pick_date": "2026-07-16",
        "entry_price": 6390,
        "watering_target_price": 5981,
        "watering_weight": "첫 매수와 동일 수량(1배)",
        "take_profit_target_price": 6594,
        "take_profit_after_watering_price": 6383,
        "expiry_date": "2026-07-21",
        "current_state": "running",
        "current_pnl_pct": 0.0,
        "current_mdd_pct": 0.0,
        "current_mdd_peak_pct": 0.0,
        "d_offset": 0,
        "result": null
      }
    },
    {
      "code": "413630",
      "name": "씨피시스템",
      "pm320_pick": {
        "is_pick": false,
        "pick_date": "2026-07-16",
        "entry_price": 3360,
        "watering_target_price": 3145,
        "watering_weight": "첫 매수와 동일 수량(1배)",
        "take_profit_target_price": 3468,
        "take_profit_after_watering_price": 3357,
        "expiry_date": "2026-07-21",
        "current_state": "running",
        "current_pnl_pct": 0.0,
        "current_mdd_pct": 0.0,
        "current_mdd_peak_pct": 0.0,
        "d_offset": 0,
        "result": null
      }
    },
    {
      "code": "000020",
      "name": "동화약품",
      "pm320_pick": {
        "is_pick": false,
        "pick_date": "2026-07-16",
        "entry_price": 5740,
        "watering_target_price": 5373,
        "watering_weight": "첫 매수와 동일 수량(1배)",
        "take_profit_target_price": 5924,
        "take_profit_after_watering_price": 5734,
        "expiry_date": "2026-07-21",
        "current_state": "running",
        "current_pnl_pct": 0.0,
        "current_mdd_pct": 0.0,
        "current_mdd_peak_pct": 0.0,
        "d_offset": 0,
        "result": null
      }
    },
    {
      "code": "012690",
      "name": "모나리자",
      "pm320_pick": {
        "is_pick": false,
        "pick_date": "2026-07-16",
        "entry_price": 2170,
        "watering_target_price": 2031,
        "watering_weight": "첫 매수와 동일 수량(1배)",
        "take_profit_target_price": 2239,
        "take_profit_after_watering_price": 2168,
        "expiry_date": "2026-07-21",
        "current_state": "running",
        "current_pnl_pct": 0.0,
        "current_mdd_pct": 0.0,
        "current_mdd_peak_pct": 0.0,
        "d_offset": 0,
        "result": null
      }
    },
    {
      "code": "014950",
      "name": "삼익제약",
      "pm320_pick": {
        "is_pick": false,
        "pick_date": "2026-07-16",
        "entry_price": 5570,
        "watering_target_price": 5214,
        "watering_weight": "첫 매수와 동일 수량(1배)",
        "take_profit_target_price": 5748,
        "take_profit_after_watering_price": 5564,
        "expiry_date": "2026-07-21",
        "current_state": "running",
        "current_pnl_pct": 0.0,
        "current_mdd_pct": 0.0,
        "current_mdd_peak_pct": 0.0,
        "d_offset": 0,
        "result": null
      }
    },
    {
      "code": "023790",
      "name": "동일스틸럭스",
      "pm320_pick": {
        "is_pick": false,
        "pick_date": "2026-07-16",
        "entry_price": 1583,
        "watering_target_price": 1482,
        "watering_weight": "첫 매수와 동일 수량(1배)",
        "take_profit_target_price": 1634,
        "take_profit_after_watering_price": 1581,
        "expiry_date": "2026-07-21",
        "current_state": "running",
        "current_pnl_pct": 0.0,
        "current_mdd_pct": 0.0,
        "current_mdd_peak_pct": 0.0,
        "d_offset": 0,
        "result": null
      }
    },
    {
      "code": "011090",
      "name": "에넥스",
      "pm320_pick": {
        "is_pick": false,
        "pick_date": "2026-07-16",
        "entry_price": 2755,
        "watering_target_price": 2579,
        "watering_weight": "첫 매수와 동일 수량(1배)",
        "take_profit_target_price": 2843,
        "take_profit_after_watering_price": 2752,
        "expiry_date": "2026-07-21",
        "current_state": "running",
        "current_pnl_pct": 0.0,
        "current_mdd_pct": 0.0,
        "current_mdd_peak_pct": 0.0,
        "d_offset": 0,
        "result": null
      }
    },
    {
      "code": "033340",
      "name": "좋은사람들",
      "pm320_pick": {
        "is_pick": false,
        "pick_date": "2026-07-16",
        "entry_price": 530,
        "watering_target_price": 496,
        "watering_weight": "첫 매수와 동일 수량(1배)",
        "take_profit_target_price": 547,
        "take_profit_after_watering_price": 529,
        "expiry_date": "2026-07-21",
        "current_state": "running",
        "current_pnl_pct": 0.0,
        "current_mdd_pct": 0.0,
        "current_mdd_peak_pct": 0.0,
        "d_offset": 0,
        "result": null
      }
    },
    {
      "code": "024940",
      "name": "PN풍년",
      "pm320_pick": {
        "is_pick": false,
        "pick_date": "2026-07-16",
        "entry_price": 2700,
        "watering_target_price": 2527,
        "watering_weight": "첫 매수와 동일 수량(1배)",
        "take_profit_target_price": 2786,
        "take_profit_after_watering_price": 2697,
        "expiry_date": "2026-07-21",
        "current_state": "running",
        "current_pnl_pct": 0.0,
        "current_mdd_pct": 0.0,
        "current_mdd_peak_pct": 0.0,
        "d_offset": 0,
        "result": null
      }
    },
    {
      "code": "285800",
      "name": "진영",
      "pm320_pick": {
        "is_pick": false,
        "pick_date": "2026-07-16",
        "entry_price": 1093,
        "watering_target_price": 1023,
        "watering_weight": "첫 매수와 동일 수량(1배)",
        "take_profit_target_price": 1128,
        "take_profit_after_watering_price": 1092,
        "expiry_date": "2026-07-21",
        "current_state": "running",
        "current_pnl_pct": 0.0,
        "current_mdd_pct": 0.0,
        "current_mdd_peak_pct": 0.0,
        "d_offset": 0,
        "result": null
      }
    },
    {
      "code": "072770",
      "name": "멤레이비티",
      "pm320_pick": {
        "is_pick": false,
        "pick_date": "2026-07-16",
        "entry_price": 1053,
        "watering_target_price": 986,
        "watering_weight": "첫 매수와 동일 수량(1배)",
        "take_profit_target_price": 1087,
        "take_profit_after_watering_price": 1052,
        "expiry_date": "2026-07-21",
        "current_state": "running",
        "current_pnl_pct": 0.0,
        "current_mdd_pct": 0.0,
        "current_mdd_peak_pct": 0.0,
        "d_offset": 0,
        "result": null
      }
    },
    {
      "code": "015260",
      "name": "에이엔피",
      "pm320_pick": {
        "is_pick": false,
        "pick_date": "2026-07-16",
        "entry_price": 435,
        "watering_target_price": 407,
        "watering_weight": "첫 매수와 동일 수량(1배)",
        "take_profit_target_price": 449,
        "take_profit_after_watering_price": 435,
        "expiry_date": "2026-07-21",
        "current_state": "running",
        "current_pnl_pct": 0.0,
        "current_mdd_pct": 0.0,
        "current_mdd_peak_pct": 0.0,
        "d_offset": 0,
        "result": null
      }
    },
    {
      "code": "093240",
      "name": "형지엘리트",
      "pm320_pick": {
        "is_pick": false,
        "pick_date": "2026-07-16",
        "entry_price": 735,
        "watering_target_price": 688,
        "watering_weight": "첫 매수와 동일 수량(1배)",
        "take_profit_target_price": 759,
        "take_profit_after_watering_price": 734,
        "expiry_date": "2026-07-21",
        "current_state": "running",
        "current_pnl_pct": 0.0,
        "current_mdd_pct": 0.0,
        "current_mdd_peak_pct": 0.0,
        "d_offset": 0,
        "result": null
      }
    },
    {
      "code": "066910",
      "name": "손오공",
      "pm320_pick": {
        "is_pick": false,
        "pick_date": "2026-07-16",
        "entry_price": 2285,
        "watering_target_price": 2139,
        "watering_weight": "첫 매수와 동일 수량(1배)",
        "take_profit_target_price": 2358,
        "take_profit_after_watering_price": 2283,
        "expiry_date": "2026-07-21",
        "current_state": "running",
        "current_pnl_pct": 0.0,
        "current_mdd_pct": 0.0,
        "current_mdd_peak_pct": 0.0,
        "d_offset": 0,
        "result": null
      }
    },
    {
      "code": "308100",
      "name": "형지글로벌",
      "pm320_pick": {
        "is_pick": false,
        "pick_date": "2026-07-16",
        "entry_price": 656,
        "watering_target_price": 614,
        "watering_weight": "첫 매수와 동일 수량(1배)",
        "take_profit_target_price": 677,
        "take_profit_after_watering_price": 655,
        "expiry_date": "2026-07-21",
        "current_state": "running",
        "current_pnl_pct": 0.0,
        "current_mdd_pct": null,
        "current_mdd_peak_pct": null,
        "d_offset": 0,
        "result": null
      }
    },
    {
      "code": "002070",
      "name": "비비안",
      "pm320_pick": {
        "is_pick": false,
        "pick_date": "2026-07-16",
        "entry_price": 13800,
        "watering_target_price": 12917,
        "watering_weight": "첫 매수와 동일 수량(1배)",
        "take_profit_target_price": 14242,
        "take_profit_after_watering_price": 13786,
        "expiry_date": "2026-07-21",
        "current_state": "running",
        "current_pnl_pct": 0.0,
        "current_mdd_pct": 0.0,
        "current_mdd_peak_pct": 0.0,
        "d_offset": 0,
        "result": null
      }
    },
    {
      "code": "011080",
      "name": "형지I&C",
      "pm320_pick": {
        "is_pick": false,
        "pick_date": "2026-07-16",
        "entry_price": 2865,
        "watering_target_price": 2682,
        "watering_weight": "첫 매수와 동일 수량(1배)",
        "take_profit_target_price": 2957,
        "take_profit_after_watering_price": 2862,
        "expiry_date": "2026-07-21",
        "current_state": "running",
        "current_pnl_pct": 0.0,
        "current_mdd_pct": 0.0,
        "current_mdd_peak_pct": 0.0,
        "d_offset": 0,
        "result": null
      }
    },
    {
      "code": "044380",
      "name": "주연테크",
      "pm320_pick": {
        "is_pick": false,
        "pick_date": "2026-07-16",
        "entry_price": 1040,
        "watering_target_price": 973,
        "watering_weight": "첫 매수와 동일 수량(1배)",
        "take_profit_target_price": 1073,
        "take_profit_after_watering_price": 1039,
        "expiry_date": "2026-07-21",
        "current_state": "running",
        "current_pnl_pct": 0.0,
        "current_mdd_pct": null,
        "current_mdd_peak_pct": null,
        "d_offset": 0,
        "result": null
      }
    }
  ],
  "_meta": {
    "pick_count": 1,
    "virtual_count": 21,
    "skip_count": 0,
    "total_cards": 22,
    "expired_count": 0,
    "running_count": 22
  }
}
