{
  "date": "2026-04-30",
  "generated_at": "2026-06-11T20:05:08+09:00",
  "picked_code": "001440",
  "stocks": [
    {
      "code": "001440",
      "name": "대한전선",
      "pm320_pick": {
        "is_pick": true,
        "pick_date": "2026-04-30",
        "entry_price": 56300,
        "watering_target_price": 52697,
        "watering_weight": "첫 매수와 동일 수량(1배)",
        "take_profit_target_price": 58102,
        "take_profit_after_watering_price": 56242,
        "expiry_date": "2026-05-07",
        "current_state": "taken_profit",
        "current_pnl_pct": 3.2,
        "current_mdd_pct": null,
        "current_mdd_peak_pct": null,
        "d_offset": 26,
        "result": {
          "final_price": 58102,
          "final_pnl_pct": 3.2,
          "watered": false,
          "result_date": "2026-05-04",
          "same_day_afterhours": false,
          "current_partial": false
        }
      }
    },
    {
      "code": "006340",
      "name": "대원전선",
      "pm320_pick": {
        "is_pick": false,
        "pick_date": "2026-04-30",
        "entry_price": 15050,
        "watering_target_price": 14087,
        "watering_weight": "첫 매수와 동일 수량(1배)",
        "take_profit_target_price": 15532,
        "take_profit_after_watering_price": 15035,
        "expiry_date": "2026-05-07",
        "current_state": "taken_profit",
        "current_pnl_pct": 3.2,
        "current_mdd_pct": null,
        "current_mdd_peak_pct": null,
        "d_offset": 26,
        "result": {
          "final_price": 15532,
          "final_pnl_pct": 3.2,
          "watered": false,
          "result_date": "2026-05-04",
          "mdd_pct": 0.0,
          "mdd_peak_pct": -3.765
        }
      }
    },
    {
      "code": "062040",
      "name": "산일전기",
      "pm320_pick": {
        "is_pick": false,
        "pick_date": "2026-04-30",
        "entry_price": 266000,
        "watering_target_price": 248976,
        "watering_weight": "첫 매수와 동일 수량(1배)",
        "take_profit_target_price": 274512,
        "take_profit_after_watering_price": 265728,
        "expiry_date": "2026-05-07",
        "current_state": "taken_profit",
        "current_pnl_pct": 3.2,
        "current_mdd_pct": null,
        "current_mdd_peak_pct": null,
        "d_offset": 26,
        "result": {
          "final_price": 274512,
          "final_pnl_pct": 3.2,
          "watered": false,
          "result_date": "2026-05-04",
          "mdd_pct": 0.0,
          "mdd_peak_pct": -3.261
        }
      }
    },
    {
      "code": "025860",
      "name": "남해화학",
      "pm320_pick": {
        "is_pick": false,
        "pick_date": "2026-04-30",
        "entry_price": 11740,
        "watering_target_price": 10989,
        "watering_weight": "첫 매수와 동일 수량(1배)",
        "take_profit_target_price": 12116,
        "take_profit_after_watering_price": 11728,
        "expiry_date": "2026-05-07",
        "current_state": "taken_profit",
        "current_pnl_pct": 3.2,
        "current_mdd_pct": null,
        "current_mdd_peak_pct": null,
        "d_offset": 26,
        "result": {
          "final_price": 12116,
          "final_pnl_pct": 3.2,
          "watered": false,
          "result_date": "2026-05-04",
          "mdd_pct": 0.0,
          "mdd_peak_pct": -5.694
        }
      }
    },
    {
      "code": "199820",
      "name": "제일일렉트릭",
      "pm320_pick": {
        "is_pick": false,
        "pick_date": "2026-04-30",
        "entry_price": 17260,
        "watering_target_price": 16155,
        "watering_weight": "첫 매수와 동일 수량(1배)",
        "take_profit_target_price": 17812,
        "take_profit_after_watering_price": 17242,
        "expiry_date": "2026-05-07",
        "current_state": "taken_profit",
        "current_pnl_pct": 3.2,
        "current_mdd_pct": null,
        "current_mdd_peak_pct": null,
        "d_offset": 26,
        "result": {
          "final_price": 17812,
          "final_pnl_pct": 3.2,
          "watered": false,
          "result_date": "2026-05-04",
          "mdd_pct": 0.0,
          "mdd_peak_pct": -3.407
        }
      }
    },
    {
      "code": "322000",
      "name": "HD현대에너지솔루션",
      "pm320_pick": {
        "is_pick": false,
        "pick_date": "2026-04-30",
        "entry_price": 231000,
        "watering_target_price": 216216,
        "watering_weight": "첫 매수와 동일 수량(1배)",
        "take_profit_target_price": 238392,
        "take_profit_after_watering_price": 230763,
        "expiry_date": "2026-05-12",
        "current_state": "expired_loss",
        "current_pnl_pct": -7.33,
        "current_mdd_pct": null,
        "current_mdd_peak_pct": null,
        "d_offset": 26,
        "result": {
          "final_price": 207000,
          "final_pnl_pct": -7.33,
          "watered": true,
          "result_date": "2026-05-12",
          "mdd_pct": -15.832,
          "mdd_peak_pct": -19.313
        }
      }
    },
    {
      "code": "046890",
      "name": "서울반도체",
      "pm320_pick": {
        "is_pick": false,
        "pick_date": "2026-04-30",
        "entry_price": 16510,
        "watering_target_price": 15453,
        "watering_weight": "첫 매수와 동일 수량(1배)",
        "take_profit_target_price": 17038,
        "take_profit_after_watering_price": 16493,
        "expiry_date": "2026-05-07",
        "current_state": "taken_profit",
        "current_pnl_pct": 3.2,
        "current_mdd_pct": null,
        "current_mdd_peak_pct": null,
        "d_offset": 26,
        "result": {
          "final_price": 17038,
          "final_pnl_pct": 3.2,
          "watered": false,
          "result_date": "2026-05-04",
          "mdd_pct": 0.0,
          "mdd_peak_pct": -7.213
        }
      }
    },
    {
      "code": "432720",
      "name": "퀄리타스반도체",
      "pm320_pick": {
        "is_pick": false,
        "pick_date": "2026-04-30",
        "entry_price": 25050,
        "watering_target_price": 23447,
        "watering_weight": "첫 매수와 동일 수량(1배)",
        "take_profit_target_price": 25852,
        "take_profit_after_watering_price": 25024,
        "expiry_date": "2026-05-07",
        "current_state": "taken_profit",
        "current_pnl_pct": 3.2,
        "current_mdd_pct": null,
        "current_mdd_peak_pct": null,
        "d_offset": 26,
        "result": {
          "final_price": 25852,
          "final_pnl_pct": 3.2,
          "watered": false,
          "result_date": "2026-05-04",
          "mdd_pct": 0.0,
          "mdd_peak_pct": -5.273
        }
      }
    },
    {
      "code": "178320",
      "name": "서진시스템",
      "pm320_pick": {
        "is_pick": false,
        "pick_date": "2026-04-30",
        "entry_price": 59500,
        "watering_target_price": 55692,
        "watering_weight": "첫 매수와 동일 수량(1배)",
        "take_profit_target_price": 61404,
        "take_profit_after_watering_price": 59439,
        "expiry_date": "2026-05-07",
        "current_state": "taken_profit",
        "current_pnl_pct": 3.2,
        "current_mdd_pct": null,
        "current_mdd_peak_pct": null,
        "d_offset": 26,
        "result": {
          "final_price": 61404,
          "final_pnl_pct": 3.2,
          "watered": false,
          "result_date": "2026-05-04",
          "mdd_pct": -0.336,
          "mdd_peak_pct": -4.2
        }
      }
    },
    {
      "code": "125020",
      "name": "티씨머티리얼즈",
      "pm320_pick": {
        "is_pick": false,
        "pick_date": "2026-04-30",
        "entry_price": 8430,
        "watering_target_price": 7890,
        "watering_weight": "첫 매수와 동일 수량(1배)",
        "take_profit_target_price": 8700,
        "take_profit_after_watering_price": 8421,
        "expiry_date": "2026-05-07",
        "current_state": "taken_profit",
        "current_pnl_pct": 3.2,
        "current_mdd_pct": null,
        "current_mdd_peak_pct": null,
        "d_offset": 26,
        "result": {
          "final_price": 8700,
          "final_pnl_pct": 3.2,
          "watered": false,
          "result_date": "2026-05-04",
          "mdd_pct": 0.0,
          "mdd_peak_pct": -3.452
        }
      }
    },
    {
      "code": "024840",
      "name": "KBI메탈",
      "pm320_pick": {
        "is_pick": false,
        "pick_date": "2026-04-30",
        "entry_price": 5100,
        "watering_target_price": 4774,
        "watering_weight": "첫 매수와 동일 수량(1배)",
        "take_profit_target_price": 5263,
        "take_profit_after_watering_price": 5095,
        "expiry_date": "2026-05-07",
        "current_state": "taken_profit",
        "current_pnl_pct": 3.2,
        "current_mdd_pct": null,
        "current_mdd_peak_pct": null,
        "d_offset": 26,
        "result": {
          "final_price": 5263,
          "final_pnl_pct": 3.2,
          "watered": false,
          "result_date": "2026-05-04",
          "mdd_pct": 0.0,
          "mdd_peak_pct": -9.306
        }
      }
    },
    {
      "code": "475150",
      "name": "SK이터닉스",
      "pm320_pick": {
        "is_pick": false,
        "pick_date": "2026-04-30",
        "entry_price": 58000,
        "watering_target_price": 54288,
        "watering_weight": "첫 매수와 동일 수량(1배)",
        "take_profit_target_price": 59856,
        "take_profit_after_watering_price": 57941,
        "expiry_date": "2026-05-12",
        "current_state": "expired_loss",
        "current_pnl_pct": -5.85,
        "current_mdd_pct": null,
        "current_mdd_peak_pct": null,
        "d_offset": 26,
        "result": {
          "final_price": 52800,
          "final_pnl_pct": -5.85,
          "watered": true,
          "result_date": "2026-05-12",
          "mdd_pct": -18.691,
          "mdd_peak_pct": -21.379
        }
      }
    },
    {
      "code": "440110",
      "name": "파두",
      "pm320_pick": {
        "is_pick": false,
        "pick_date": "2026-04-30",
        "entry_price": 78200,
        "watering_target_price": 73195,
        "watering_weight": "첫 매수와 동일 수량(1배)",
        "take_profit_target_price": 80702,
        "take_profit_after_watering_price": 78120,
        "expiry_date": "2026-05-07",
        "current_state": "taken_profit",
        "current_pnl_pct": 3.2,
        "current_mdd_pct": null,
        "current_mdd_peak_pct": null,
        "d_offset": 26,
        "result": {
          "final_price": 80702,
          "final_pnl_pct": 3.2,
          "watered": false,
          "result_date": "2026-05-04",
          "mdd_pct": 0.0,
          "mdd_peak_pct": -2.916
        }
      }
    },
    {
      "code": "006260",
      "name": "LS",
      "pm320_pick": {
        "is_pick": false,
        "pick_date": "2026-04-30",
        "entry_price": 453000,
        "watering_target_price": 424008,
        "watering_weight": "첫 매수와 동일 수량(1배)",
        "take_profit_target_price": 467496,
        "take_profit_after_watering_price": 452536,
        "expiry_date": "2026-05-07",
        "current_state": "taken_profit",
        "current_pnl_pct": 3.2,
        "current_mdd_pct": null,
        "current_mdd_peak_pct": null,
        "d_offset": 26,
        "result": {
          "final_price": 467496,
          "final_pnl_pct": 3.2,
          "watered": false,
          "result_date": "2026-05-04",
          "mdd_pct": 0.0,
          "mdd_peak_pct": -4.025
        }
      }
    },
    {
      "code": "147830",
      "name": "제룡산업",
      "pm320_pick": {
        "is_pick": false,
        "pick_date": "2026-04-30",
        "entry_price": 11690,
        "watering_target_price": 10942,
        "watering_weight": "첫 매수와 동일 수량(1배)",
        "take_profit_target_price": 12064,
        "take_profit_after_watering_price": 11678,
        "expiry_date": "2026-05-07",
        "current_state": "taken_profit",
        "current_pnl_pct": 3.2,
        "current_mdd_pct": null,
        "current_mdd_peak_pct": null,
        "d_offset": 26,
        "result": {
          "final_price": 12064,
          "final_pnl_pct": 3.2,
          "watered": false,
          "result_date": "2026-05-04",
          "mdd_pct": 0.0,
          "mdd_peak_pct": 0.0
        }
      }
    },
    {
      "code": "059120",
      "name": "아진엑스텍",
      "pm320_pick": {
        "is_pick": false,
        "pick_date": "2026-04-30",
        "entry_price": 8910,
        "watering_target_price": 8340,
        "watering_weight": "첫 매수와 동일 수량(1배)",
        "take_profit_target_price": 9195,
        "take_profit_after_watering_price": 8901,
        "expiry_date": "2026-05-07",
        "current_state": "taken_profit",
        "current_pnl_pct": 3.2,
        "current_mdd_pct": null,
        "current_mdd_peak_pct": null,
        "d_offset": 26,
        "result": {
          "final_price": 9195,
          "final_pnl_pct": 3.2,
          "watered": false,
          "result_date": "2026-05-04",
          "mdd_pct": 0.0,
          "mdd_peak_pct": -5.112
        }
      }
    },
    {
      "code": "103590",
      "name": "일진전기",
      "pm320_pick": {
        "is_pick": false,
        "pick_date": "2026-04-30",
        "entry_price": 122500,
        "watering_target_price": 114660,
        "watering_weight": "첫 매수와 동일 수량(1배)",
        "take_profit_target_price": 126420,
        "take_profit_after_watering_price": 122375,
        "expiry_date": "2026-05-07",
        "current_state": "taken_profit",
        "current_pnl_pct": 3.2,
        "current_mdd_pct": null,
        "current_mdd_peak_pct": null,
        "d_offset": 26,
        "result": {
          "final_price": 126420,
          "final_pnl_pct": 3.2,
          "watered": false,
          "result_date": "2026-05-04",
          "mdd_pct": 0.0,
          "mdd_peak_pct": -3.391
        }
      }
    },
    {
      "code": "490470",
      "name": "세미파이브",
      "pm320_pick": {
        "is_pick": false,
        "pick_date": "2026-04-30",
        "entry_price": 42450,
        "watering_target_price": 39733,
        "watering_weight": "첫 매수와 동일 수량(1배)",
        "take_profit_target_price": 43808,
        "take_profit_after_watering_price": 42407,
        "expiry_date": "2026-05-07",
        "current_state": "taken_profit",
        "current_pnl_pct": 3.2,
        "current_mdd_pct": null,
        "current_mdd_peak_pct": null,
        "d_offset": 26,
        "result": {
          "final_price": 43808,
          "final_pnl_pct": 3.2,
          "watered": false,
          "result_date": "2026-05-04",
          "mdd_pct": 0.0,
          "mdd_peak_pct": -2.766
        }
      }
    },
    {
      "code": "017510",
      "name": "세명전기",
      "pm320_pick": {
        "is_pick": false,
        "pick_date": "2026-04-30",
        "entry_price": 14500,
        "watering_target_price": 13572,
        "watering_weight": "첫 매수와 동일 수량(1배)",
        "take_profit_target_price": 14964,
        "take_profit_after_watering_price": 14485,
        "expiry_date": "2026-05-07",
        "current_state": "taken_profit",
        "current_pnl_pct": 3.2,
        "current_mdd_pct": null,
        "current_mdd_peak_pct": null,
        "d_offset": 26,
        "result": {
          "final_price": 14964,
          "final_pnl_pct": 3.2,
          "watered": false,
          "result_date": "2026-05-04",
          "mdd_pct": 0.0,
          "mdd_peak_pct": 0.0
        }
      }
    },
    {
      "code": "041910",
      "name": "폴라리스AI파마",
      "pm320_pick": {
        "is_pick": false,
        "pick_date": "2026-04-30",
        "entry_price": 7480,
        "watering_target_price": 7001,
        "watering_weight": "첫 매수와 동일 수량(1배)",
        "take_profit_target_price": 7719,
        "take_profit_after_watering_price": 7472,
        "expiry_date": "2026-05-12",
        "current_state": "taken_profit",
        "current_pnl_pct": 3.2,
        "current_mdd_pct": null,
        "current_mdd_peak_pct": null,
        "d_offset": 26,
        "result": {
          "final_price": 7464,
          "final_pnl_pct": 3.2,
          "watered": true,
          "result_date": "2026-05-07",
          "mdd_pct": -6.417,
          "mdd_peak_pct": -9.233
        }
      }
    },
    {
      "code": "033100",
      "name": "제룡전기",
      "pm320_pick": {
        "is_pick": false,
        "pick_date": "2026-04-30",
        "entry_price": 70400,
        "watering_target_price": 65894,
        "watering_weight": "첫 매수와 동일 수량(1배)",
        "take_profit_target_price": 72653,
        "take_profit_after_watering_price": 70328,
        "expiry_date": "2026-05-07",
        "current_state": "taken_profit",
        "current_pnl_pct": 3.2,
        "current_mdd_pct": null,
        "current_mdd_peak_pct": null,
        "d_offset": 26,
        "result": {
          "final_price": 72653,
          "final_pnl_pct": 3.2,
          "watered": false,
          "result_date": "2026-05-04",
          "mdd_pct": -1.278,
          "mdd_peak_pct": -3.472
        }
      }
    },
    {
      "code": "396300",
      "name": "세아메카닉스",
      "pm320_pick": {
        "is_pick": false,
        "pick_date": "2026-04-30",
        "entry_price": 5900,
        "watering_target_price": 5522,
        "watering_weight": "첫 매수와 동일 수량(1배)",
        "take_profit_target_price": 6089,
        "take_profit_after_watering_price": 5894,
        "expiry_date": "2026-05-07",
        "current_state": "taken_profit",
        "current_pnl_pct": 3.2,
        "current_mdd_pct": null,
        "current_mdd_peak_pct": null,
        "d_offset": 26,
        "result": {
          "final_price": 6089,
          "final_pnl_pct": 3.2,
          "watered": false,
          "result_date": "2026-05-04",
          "mdd_pct": 0.0,
          "mdd_peak_pct": -3.611
        }
      }
    },
    {
      "code": "039980",
      "name": "폴라리스AI",
      "pm320_pick": {
        "is_pick": false,
        "pick_date": "2026-04-30",
        "entry_price": 9300,
        "watering_target_price": 8705,
        "watering_weight": "첫 매수와 동일 수량(1배)",
        "take_profit_target_price": 9598,
        "take_profit_after_watering_price": 9290,
        "expiry_date": "2026-05-07",
        "current_state": "taken_profit",
        "current_pnl_pct": 3.2,
        "current_mdd_pct": null,
        "current_mdd_peak_pct": null,
        "d_offset": 26,
        "result": {
          "final_price": 9598,
          "final_pnl_pct": 3.2,
          "watered": false,
          "result_date": "2026-05-04",
          "mdd_pct": -5.269,
          "mdd_peak_pct": -5.371
        }
      }
    },
    {
      "code": "336260",
      "name": "두산퓨얼셀",
      "pm320_pick": {
        "is_pick": false,
        "pick_date": "2026-04-30",
        "entry_price": 60800,
        "watering_target_price": 56909,
        "watering_weight": "첫 매수와 동일 수량(1배)",
        "take_profit_target_price": 62746,
        "take_profit_after_watering_price": 60738,
        "expiry_date": "2026-05-12",
        "current_state": "taken_profit",
        "current_pnl_pct": 3.2,
        "current_mdd_pct": null,
        "current_mdd_peak_pct": null,
        "d_offset": 26,
        "result": {
          "final_price": 60671,
          "final_pnl_pct": 3.2,
          "watered": true,
          "result_date": "2026-05-04",
          "mdd_pct": -7.895,
          "mdd_peak_pct": -9.238
        }
      }
    },
    {
      "code": "340440",
      "name": "세림B&G",
      "pm320_pick": {
        "is_pick": false,
        "pick_date": "2026-04-30",
        "entry_price": 2510,
        "watering_target_price": 2349,
        "watering_weight": "첫 매수와 동일 수량(1배)",
        "take_profit_target_price": 2590,
        "take_profit_after_watering_price": 2507,
        "expiry_date": "2026-05-12",
        "current_state": "expired_loss",
        "current_pnl_pct": -25.09,
        "current_mdd_pct": null,
        "current_mdd_peak_pct": null,
        "d_offset": 26,
        "result": {
          "final_price": 1818,
          "final_pnl_pct": -25.09,
          "watered": true,
          "result_date": "2026-05-12",
          "mdd_pct": -27.689,
          "mdd_peak_pct": -28.367
        }
      }
    },
    {
      "code": "456160",
      "name": "지투지바이오",
      "pm320_pick": {
        "is_pick": false,
        "pick_date": "2026-04-30",
        "entry_price": 85600,
        "watering_target_price": 80122,
        "watering_weight": "첫 매수와 동일 수량(1배)",
        "take_profit_target_price": 88339,
        "take_profit_after_watering_price": 85512,
        "expiry_date": "2026-05-12",
        "current_state": "expired_loss",
        "current_pnl_pct": -11.32,
        "current_mdd_pct": null,
        "current_mdd_peak_pct": null,
        "d_offset": 26,
        "result": {
          "final_price": 73400,
          "final_pnl_pct": -11.32,
          "watered": true,
          "result_date": "2026-05-12",
          "mdd_pct": -18.932,
          "mdd_peak_pct": -23.923
        }
      }
    },
    {
      "code": "261780",
      "name": "차백신연구소",
      "pm320_pick": {
        "is_pick": false,
        "pick_date": "2026-04-30",
        "entry_price": 4100,
        "watering_target_price": 3838,
        "watering_weight": "첫 매수와 동일 수량(1배)",
        "take_profit_target_price": 4231,
        "take_profit_after_watering_price": 4096,
        "expiry_date": "2026-05-07",
        "current_state": "taken_profit",
        "current_pnl_pct": 3.2,
        "current_mdd_pct": null,
        "current_mdd_peak_pct": null,
        "d_offset": 26,
        "result": {
          "final_price": 4231,
          "final_pnl_pct": 3.2,
          "watered": false,
          "result_date": "2026-05-04",
          "mdd_pct": -0.366,
          "mdd_peak_pct": -5.537
        }
      }
    },
    {
      "code": "452190",
      "name": "한빛레이저",
      "pm320_pick": {
        "is_pick": false,
        "pick_date": "2026-04-30",
        "entry_price": 7960,
        "watering_target_price": 7451,
        "watering_weight": "첫 매수와 동일 수량(1배)",
        "take_profit_target_price": 8215,
        "take_profit_after_watering_price": 7952,
        "expiry_date": "2026-05-07",
        "current_state": "taken_profit",
        "current_pnl_pct": 3.2,
        "current_mdd_pct": null,
        "current_mdd_peak_pct": null,
        "d_offset": 26,
        "result": {
          "final_price": 8215,
          "final_pnl_pct": 3.2,
          "watered": false,
          "result_date": "2026-05-04",
          "mdd_pct": 0.0,
          "mdd_peak_pct": -3.106
        }
      }
    },
    {
      "code": "076610",
      "name": "해성옵틱스",
      "pm320_pick": {
        "is_pick": false,
        "pick_date": "2026-04-30",
        "entry_price": 1739,
        "watering_target_price": 1628,
        "watering_weight": "첫 매수와 동일 수량(1배)",
        "take_profit_target_price": 1795,
        "take_profit_after_watering_price": 1737,
        "expiry_date": "2026-05-07",
        "current_state": "taken_profit",
        "current_pnl_pct": 3.2,
        "current_mdd_pct": null,
        "current_mdd_peak_pct": null,
        "d_offset": 26,
        "result": {
          "final_price": 1795,
          "final_pnl_pct": 3.2,
          "watered": false,
          "result_date": "2026-05-04",
          "mdd_pct": 0.0,
          "mdd_peak_pct": -7.828
        }
      }
    },
    {
      "code": "254490",
      "name": "미래반도체",
      "pm320_pick": {
        "is_pick": false,
        "pick_date": "2026-04-30",
        "entry_price": 23350,
        "watering_target_price": 21856,
        "watering_weight": "첫 매수와 동일 수량(1배)",
        "take_profit_target_price": 24097,
        "take_profit_after_watering_price": 23326,
        "expiry_date": "2026-05-07",
        "current_state": "taken_profit",
        "current_pnl_pct": 3.2,
        "current_mdd_pct": null,
        "current_mdd_peak_pct": null,
        "d_offset": 26,
        "result": {
          "final_price": 24097,
          "final_pnl_pct": 3.2,
          "watered": false,
          "result_date": "2026-05-04",
          "mdd_pct": 0.0,
          "mdd_peak_pct": -6.287
        }
      }
    },
    {
      "code": "033790",
      "name": "피노",
      "pm320_pick": {
        "is_pick": false,
        "pick_date": "2026-04-30",
        "entry_price": 13580,
        "watering_target_price": 12711,
        "watering_weight": "첫 매수와 동일 수량(1배)",
        "take_profit_target_price": 14015,
        "take_profit_after_watering_price": 13566,
        "expiry_date": "2026-05-07",
        "current_state": "taken_profit",
        "current_pnl_pct": 3.2,
        "current_mdd_pct": null,
        "current_mdd_peak_pct": null,
        "d_offset": 26,
        "result": {
          "final_price": 14015,
          "final_pnl_pct": 3.2,
          "watered": false,
          "result_date": "2026-05-04",
          "mdd_pct": 0.0,
          "mdd_peak_pct": -4.729
        }
      }
    },
    {
      "code": "459510",
      "name": "나우로보틱스",
      "pm320_pick": {
        "is_pick": false,
        "pick_date": "2026-04-30",
        "entry_price": 30550,
        "watering_target_price": 28595,
        "watering_weight": "첫 매수와 동일 수량(1배)",
        "take_profit_target_price": 31528,
        "take_profit_after_watering_price": 30519,
        "expiry_date": "2026-05-07",
        "current_state": "taken_profit",
        "current_pnl_pct": 3.2,
        "current_mdd_pct": null,
        "current_mdd_peak_pct": null,
        "d_offset": 26,
        "result": {
          "final_price": 31528,
          "final_pnl_pct": 3.2,
          "watered": false,
          "result_date": "2026-05-04",
          "mdd_pct": 0.0,
          "mdd_peak_pct": -4.394
        }
      }
    },
    {
      "code": "092190",
      "name": "서울바이오시스",
      "pm320_pick": {
        "is_pick": false,
        "pick_date": "2026-04-30",
        "entry_price": 8640,
        "watering_target_price": 8087,
        "watering_weight": "첫 매수와 동일 수량(1배)",
        "take_profit_target_price": 8916,
        "take_profit_after_watering_price": 8631,
        "expiry_date": "2026-05-07",
        "current_state": "taken_profit",
        "current_pnl_pct": 3.2,
        "current_mdd_pct": null,
        "current_mdd_peak_pct": null,
        "d_offset": 26,
        "result": {
          "final_price": 8916,
          "final_pnl_pct": 3.2,
          "watered": false,
          "result_date": "2026-05-04",
          "mdd_pct": 0.0,
          "mdd_peak_pct": -17.097
        }
      }
    },
    {
      "code": "007610",
      "name": "선도전기",
      "pm320_pick": {
        "is_pick": false,
        "pick_date": "2026-04-30",
        "entry_price": 8450,
        "watering_target_price": 7909,
        "watering_weight": "첫 매수와 동일 수량(1배)",
        "take_profit_target_price": 8720,
        "take_profit_after_watering_price": 8441,
        "expiry_date": "2026-05-07",
        "current_state": "taken_profit",
        "current_pnl_pct": 3.2,
        "current_mdd_pct": null,
        "current_mdd_peak_pct": null,
        "d_offset": 26,
        "result": {
          "final_price": 8720,
          "final_pnl_pct": 3.2,
          "watered": false,
          "result_date": "2026-05-04",
          "mdd_pct": 0.0,
          "mdd_peak_pct": 0.0
        }
      }
    },
    {
      "code": "115160",
      "name": "휴맥스",
      "pm320_pick": {
        "is_pick": false,
        "pick_date": "2026-04-30",
        "entry_price": 9370,
        "watering_target_price": 8770,
        "watering_weight": "첫 매수와 동일 수량(1배)",
        "take_profit_target_price": 9670,
        "take_profit_after_watering_price": 9360,
        "expiry_date": "2026-05-07",
        "current_state": "taken_profit",
        "current_pnl_pct": 3.2,
        "current_mdd_pct": null,
        "current_mdd_peak_pct": null,
        "d_offset": 26,
        "result": {
          "final_price": 9670,
          "final_pnl_pct": 3.2,
          "watered": false,
          "result_date": "2026-05-04",
          "mdd_pct": 0.0,
          "mdd_peak_pct": -9.962
        }
      }
    },
    {
      "code": "403550",
      "name": "쏘카",
      "pm320_pick": {
        "is_pick": false,
        "pick_date": "2026-04-30",
        "entry_price": 17810,
        "watering_target_price": 16670,
        "watering_weight": "첫 매수와 동일 수량(1배)",
        "take_profit_target_price": 18380,
        "take_profit_after_watering_price": 17792,
        "expiry_date": "2026-05-07",
        "current_state": "taken_profit",
        "current_pnl_pct": 3.2,
        "current_mdd_pct": null,
        "current_mdd_peak_pct": null,
        "d_offset": 26,
        "result": {
          "final_price": 18380,
          "final_pnl_pct": 3.2,
          "watered": false,
          "result_date": "2026-05-04",
          "mdd_pct": 0.0,
          "mdd_peak_pct": -8.423
        }
      }
    },
    {
      "code": "028080",
      "name": "휴맥스홀딩스",
      "pm320_pick": {
        "is_pick": false,
        "pick_date": "2026-04-30",
        "entry_price": 9770,
        "watering_target_price": 9145,
        "watering_weight": "첫 매수와 동일 수량(1배)",
        "take_profit_target_price": 10083,
        "take_profit_after_watering_price": 9760,
        "expiry_date": "2026-05-07",
        "current_state": "taken_profit",
        "current_pnl_pct": 3.2,
        "current_mdd_pct": null,
        "current_mdd_peak_pct": null,
        "d_offset": 26,
        "result": {
          "final_price": 10083,
          "final_pnl_pct": 3.2,
          "watered": false,
          "result_date": "2026-05-04",
          "mdd_pct": 0.0,
          "mdd_peak_pct": -9.116
        }
      }
    },
    {
      "code": "101930",
      "name": "인화정공",
      "pm320_pick": {
        "is_pick": false,
        "pick_date": "2026-04-30",
        "entry_price": 13520,
        "watering_target_price": 12655,
        "watering_weight": "첫 매수와 동일 수량(1배)",
        "take_profit_target_price": 13953,
        "take_profit_after_watering_price": 13506,
        "expiry_date": "2026-05-07",
        "current_state": "taken_profit",
        "current_pnl_pct": 3.2,
        "current_mdd_pct": null,
        "current_mdd_peak_pct": null,
        "d_offset": 26,
        "result": {
          "final_price": 13953,
          "final_pnl_pct": 3.2,
          "watered": false,
          "result_date": "2026-05-04",
          "mdd_pct": 0.0,
          "mdd_peak_pct": 0.0
        }
      }
    },
    {
      "code": "377030",
      "name": "비트맥스",
      "pm320_pick": {
        "is_pick": false,
        "pick_date": "2026-04-30",
        "entry_price": 3430,
        "watering_target_price": 3210,
        "watering_weight": "첫 매수와 동일 수량(1배)",
        "take_profit_target_price": 3540,
        "take_profit_after_watering_price": 3426,
        "expiry_date": "2026-05-07",
        "current_state": "taken_profit",
        "current_pnl_pct": 3.2,
        "current_mdd_pct": null,
        "current_mdd_peak_pct": null,
        "d_offset": 26,
        "result": {
          "final_price": 3540,
          "final_pnl_pct": 3.2,
          "watered": false,
          "result_date": "2026-05-04",
          "mdd_pct": 0.0,
          "mdd_peak_pct": -9.021
        }
      }
    }
  ],
  "_meta": {
    "pick_count": 1,
    "virtual_count": 38,
    "skip_count": 0,
    "total_cards": 39,
    "expired_count": 39,
    "running_count": 0
  }
}
