{
  "date": "2026-04-17",
  "condition_name": "500억이상",
  "first_snapshot_at": "2026-04-17T09:15:52+09:00",
  "snapshot_count": 19,
  "accumulated_stocks": {
    "319400": {
      "ticker": "319400",
      "name": "현대무벡스",
      "max_trade_amount": 196081981200,
      "max_change_pct": 9.53,
      "min_change_pct": 2.91,
      "first_seen": "09:15",
      "last_seen": "22:59",
      "appearances": 19,
      "last_price": 32400,
      "open": 32500,
      "high": 34450,
      "low": 31650
    },
    "115500": {
      "ticker": "115500",
      "name": "케이씨에스",
      "max_trade_amount": 190277523940,
      "max_change_pct": 5.51,
      "min_change_pct": -3.94,
      "first_seen": "09:15",
      "last_seen": "22:59",
      "appearances": 19,
      "last_price": 17780,
      "open": 18470,
      "high": 20300,
      "low": 16010
    },
    "077360": {
      "ticker": "077360",
      "name": "덕산하이메탈",
      "max_trade_amount": 99703174500,
      "max_change_pct": 2.44,
      "min_change_pct": -1.28,
      "first_seen": "09:15",
      "last_seen": "22:59",
      "appearances": 19,
      "last_price": 16530,
      "open": 16900,
      "high": 17650,
      "low": 16100
    },
    "100790": {
      "ticker": "100790",
      "name": "미래에셋벤처투자",
      "max_trade_amount": 1012043457000,
      "max_change_pct": 23.77,
      "min_change_pct": 16.8,
      "first_seen": "09:26",
      "last_seen": "22:59",
      "appearances": 18,
      "last_price": 46300,
      "open": 39900,
      "high": 48550,
      "low": 38000
    },
    "018880": {
      "ticker": "018880",
      "name": "한온시스템",
      "max_trade_amount": 108110383680,
      "max_change_pct": 2.94,
      "min_change_pct": 0.98,
      "first_seen": "09:26",
      "last_seen": "22:59",
      "appearances": 18,
      "last_price": 4160,
      "open": 4105,
      "high": 4370,
      "low": 4090
    },
    "027360": {
      "ticker": "027360",
      "name": "아주IB투자",
      "max_trade_amount": 480913069340,
      "max_change_pct": 16.13,
      "min_change_pct": 8.75,
      "first_seen": "09:48",
      "last_seen": "22:59",
      "appearances": 17,
      "last_price": 11930,
      "open": 11130,
      "high": 13080,
      "low": 10770
    },
    "093370": {
      "ticker": "093370",
      "name": "후성",
      "max_trade_amount": 432942042200,
      "max_change_pct": 24.6,
      "min_change_pct": 14.16,
      "first_seen": "09:48",
      "last_seen": "22:59",
      "appearances": 17,
      "last_price": 13820,
      "open": 12950,
      "high": 14430,
      "low": 12060
    },
    "457190": {
      "ticker": "457190",
      "name": "이수스페셜티케미컬",
      "max_trade_amount": 159023084000,
      "max_change_pct": 12.89,
      "min_change_pct": 7.27,
      "first_seen": "09:48",
      "last_seen": "22:59",
      "appearances": 17,
      "last_price": 111500,
      "open": 105500,
      "high": 118800,
      "low": 103300
    },
    "010820": {
      "ticker": "010820",
      "name": "퍼스텍",
      "max_trade_amount": 360101983560,
      "max_change_pct": 16.71,
      "min_change_pct": 9.38,
      "first_seen": "09:48",
      "last_seen": "22:59",
      "appearances": 17,
      "last_price": 13480,
      "open": 11840,
      "high": 14330,
      "low": 11690
    },
    "009580": {
      "ticker": "009580",
      "name": "무림P&P",
      "max_trade_amount": 123534345000,
      "max_change_pct": 4.18,
      "min_change_pct": -6.47,
      "first_seen": "09:48",
      "last_seen": "22:59",
      "appearances": 17,
      "last_price": 3630,
      "open": 3800,
      "high": 4400,
      "low": 3310
    },
    "036170": {
      "ticker": "036170",
      "name": "에이치엠넥스",
      "max_trade_amount": 96474662900,
      "max_change_pct": 25.0,
      "min_change_pct": 12.97,
      "first_seen": "09:48",
      "last_seen": "22:59",
      "appearances": 17,
      "last_price": 7700,
      "open": 6680,
      "high": 8170,
      "low": 6620
    },
    "253840": {
      "ticker": "253840",
      "name": "수젠텍",
      "max_trade_amount": 82834795680,
      "max_change_pct": 30.0,
      "min_change_pct": 21.73,
      "first_seen": "09:48",
      "last_seen": "22:59",
      "appearances": 17,
      "last_price": 6760,
      "open": 5800,
      "high": 6760,
      "low": 5640
    },
    "084650": {
      "ticker": "084650",
      "name": "랩지노믹스",
      "max_trade_amount": 84802704069,
      "max_change_pct": 21.27,
      "min_change_pct": 12.74,
      "first_seen": "09:59",
      "last_seen": "22:59",
      "appearances": 16,
      "last_price": 1803,
      "open": 1666,
      "high": 1970,
      "low": 1551
    },
    "321260": {
      "ticker": "321260",
      "name": "프로이천",
      "max_trade_amount": 95788723200,
      "max_change_pct": 25.13,
      "min_change_pct": 6.9,
      "first_seen": "10:11",
      "last_seen": "22:59",
      "appearances": 15,
      "last_price": 3030,
      "open": 2850,
      "high": 3670,
      "low": 2770
    },
    "131760": {
      "ticker": "131760",
      "name": "파인텍",
      "max_trade_amount": 106797680660,
      "max_change_pct": 21.63,
      "min_change_pct": 9.47,
      "first_seen": "10:11",
      "last_seen": "22:59",
      "appearances": 15,
      "last_price": 1210,
      "open": 1400,
      "high": 1400,
      "low": 1078
    },
    "098460": {
      "ticker": "098460",
      "name": "고영",
      "max_trade_amount": 443689554000,
      "max_change_pct": 12.5,
      "min_change_pct": 2.96,
      "first_seen": "10:11",
      "last_seen": "22:59",
      "appearances": 15,
      "last_price": 33000,
      "open": 29900,
      "high": 34800,
      "low": 29350
    },
    "062040": {
      "ticker": "062040",
      "name": "산일전기",
      "max_trade_amount": 140632972900,
      "max_change_pct": 5.4,
      "min_change_pct": 4.02,
      "first_seen": "10:24",
      "last_seen": "22:59",
      "appearances": 14,
      "last_price": 198100,
      "open": 189000,
      "high": 202500,
      "low": 188300
    },
    "293580": {
      "ticker": "293580",
      "name": "나우IB",
      "max_trade_amount": 84100611605,
      "max_change_pct": 6.35,
      "min_change_pct": 0.0,
      "first_seen": "10:24",
      "last_seen": "22:59",
      "appearances": 14,
      "last_price": 2515,
      "open": 2350,
      "high": 2920,
      "low": 2150
    },
    "096530": {
      "ticker": "096530",
      "name": "씨젠",
      "max_trade_amount": 68839676500,
      "max_change_pct": 9.84,
      "min_change_pct": 7.83,
      "first_seen": "10:24",
      "last_seen": "22:59",
      "appearances": 14,
      "last_price": 27350,
      "open": 28050,
      "high": 29300,
      "low": 26300
    },
    "065450": {
      "ticker": "065450",
      "name": "빅텍",
      "max_trade_amount": 84276457350,
      "max_change_pct": 16.3,
      "min_change_pct": 11.9,
      "first_seen": "10:35",
      "last_seen": "22:59",
      "appearances": 13,
      "last_price": 6150,
      "open": 5510,
      "high": 6540,
      "low": 5460
    },
    "209640": {
      "ticker": "209640",
      "name": "와이제이링크",
      "max_trade_amount": 105457808480,
      "max_change_pct": 29.82,
      "min_change_pct": 24.78,
      "first_seen": "10:49",
      "last_seen": "22:59",
      "appearances": 12,
      "last_price": 5920,
      "open": 4610,
      "high": 5920,
      "low": 4600
    },
    "046970": {
      "ticker": "046970",
      "name": "우리로",
      "max_trade_amount": 680791214450,
      "max_change_pct": -6.69,
      "min_change_pct": -12.89,
      "first_seen": "11:56",
      "last_seen": "22:59",
      "appearances": 11,
      "last_price": 12970,
      "open": 12000,
      "high": 16200,
      "low": 10210
    },
    "067310": {
      "ticker": "067310",
      "name": "하나마이크론",
      "max_trade_amount": 101475054100,
      "max_change_pct": 6.49,
      "min_change_pct": 4.04,
      "first_seen": "11:56",
      "last_seen": "22:59",
      "appearances": 11,
      "last_price": 36050,
      "open": 34600,
      "high": 37000,
      "low": 34100
    },
    "019170": {
      "ticker": "019170",
      "name": "신풍제약",
      "max_trade_amount": 80873486110,
      "max_change_pct": 26.48,
      "min_change_pct": 18.4,
      "first_seen": "11:56",
      "last_seen": "22:59",
      "appearances": 11,
      "last_price": 14090,
      "open": 13100,
      "high": 14400,
      "low": 12870
    },
    "082740": {
      "ticker": "082740",
      "name": "한화엔진",
      "max_trade_amount": 288555174600,
      "max_change_pct": 20.54,
      "min_change_pct": 16.39,
      "first_seen": "14:11",
      "last_seen": "22:59",
      "appearances": 10,
      "last_price": 56100,
      "open": 48700,
      "high": 59900,
      "low": 47200
    },
    "077970": {
      "ticker": "077970",
      "name": "STX엔진",
      "max_trade_amount": 159297028000,
      "max_change_pct": 29.99,
      "min_change_pct": 29.54,
      "first_seen": "14:11",
      "last_seen": "22:59",
      "appearances": 10,
      "last_price": 44000,
      "open": 34200,
      "high": 44000,
      "low": 33600
    },
    "038060": {
      "ticker": "038060",
      "name": "루멘스",
      "max_trade_amount": 72960481227,
      "max_change_pct": 5.04,
      "min_change_pct": -7.1,
      "first_seen": "14:11",
      "last_seen": "22:59",
      "appearances": 10,
      "last_price": 1531,
      "open": 1647,
      "high": 2100,
      "low": 1153
    },
    "332570": {
      "ticker": "332570",
      "name": "PS일렉트로닉스",
      "max_trade_amount": 75589324740,
      "max_change_pct": 7.36,
      "min_change_pct": 6.33,
      "first_seen": "14:11",
      "last_seen": "22:59",
      "appearances": 10,
      "last_price": 7290,
      "open": 6810,
      "high": 7440,
      "low": 6690
    },
    "131970": {
      "ticker": "131970",
      "name": "두산테스나",
      "max_trade_amount": 76513013200,
      "max_change_pct": 11.34,
      "min_change_pct": 10.45,
      "first_seen": "14:11",
      "last_seen": "22:59",
      "appearances": 10,
      "last_price": 111800,
      "open": 100600,
      "high": 112800,
      "low": 99600
    },
    "017550": {
      "ticker": "017550",
      "name": "수산세보틱스",
      "max_trade_amount": 60764791280,
      "max_change_pct": 8.6,
      "min_change_pct": 6.94,
      "first_seen": "14:11",
      "last_seen": "22:59",
      "appearances": 10,
      "last_price": 3280,
      "open": 3015,
      "high": 3570,
      "low": 2950
    },
    "090460": {
      "ticker": "090460",
      "name": "비에이치",
      "max_trade_amount": 82443745800,
      "max_change_pct": 9.93,
      "min_change_pct": 5.65,
      "first_seen": "14:11",
      "last_seen": "22:59",
      "appearances": 10,
      "last_price": 31400,
      "open": 28250,
      "high": 32150,
      "low": 27250
    },
    "150900": {
      "ticker": "150900",
      "name": "파수",
      "max_trade_amount": 55574764300,
      "max_change_pct": 4.77,
      "min_change_pct": 0.2,
      "first_seen": "14:11",
      "last_seen": "22:59",
      "appearances": 10,
      "last_price": 5060,
      "open": 4950,
      "high": 6220,
      "low": 4410
    },
    "440110": {
      "ticker": "440110",
      "name": "파두",
      "max_trade_amount": 57908146000,
      "max_change_pct": 2.43,
      "min_change_pct": 2.08,
      "first_seen": "14:11",
      "last_seen": "22:59",
      "appearances": 10,
      "last_price": 59000,
      "open": 57800,
      "high": 62500,
      "low": 56400
    },
    "388210": {
      "ticker": "388210",
      "name": "씨엠티엑스",
      "max_trade_amount": 57770537500,
      "max_change_pct": 7.04,
      "min_change_pct": 6.45,
      "first_seen": "14:11",
      "last_seen": "22:59",
      "appearances": 10,
      "last_price": 162500,
      "open": 150600,
      "high": 164500,
      "low": 149500
    },
    "071970": {
      "ticker": "071970",
      "name": "HD현대마린엔진",
      "max_trade_amount": 122257065600,
      "max_change_pct": 12.4,
      "min_change_pct": 6.67,
      "first_seen": "14:24",
      "last_seen": "22:59",
      "appearances": 9,
      "last_price": 91200,
      "open": 86200,
      "high": 98100,
      "low": 83200
    },
    "097230": {
      "ticker": "097230",
      "name": "HJ중공업",
      "max_trade_amount": 95655119100,
      "max_change_pct": 4.0,
      "min_change_pct": 3.64,
      "first_seen": "14:39",
      "last_seen": "22:59",
      "appearances": 8,
      "last_price": 28550,
      "open": 27550,
      "high": 28900,
      "low": 26750
    },
    "080580": {
      "ticker": "080580",
      "name": "오킨스전자",
      "max_trade_amount": 54110027800,
      "max_change_pct": 11.89,
      "min_change_pct": 10.35,
      "first_seen": "14:39",
      "last_seen": "22:59",
      "appearances": 8,
      "last_price": 25100,
      "open": 22700,
      "high": 26300,
      "low": 22400
    },
    "089970": {
      "ticker": "089970",
      "name": "브이엠",
      "max_trade_amount": 56083975800,
      "max_change_pct": 9.76,
      "min_change_pct": 9.36,
      "first_seen": "14:55",
      "last_seen": "22:59",
      "appearances": 7,
      "last_price": 55100,
      "open": 49800,
      "high": 56100,
      "low": 49500
    },
    "417010": {
      "ticker": "417010",
      "name": "나노팀",
      "max_trade_amount": 52754762010,
      "max_change_pct": 15.19,
      "min_change_pct": 14.8,
      "first_seen": "14:55",
      "last_seen": "22:59",
      "appearances": 7,
      "last_price": 12030,
      "open": 10480,
      "high": 12620,
      "low": 10480
    },
    "099320": {
      "ticker": "099320",
      "name": "쎄트렉아이",
      "max_trade_amount": 52404562500,
      "max_change_pct": 7.7,
      "min_change_pct": 7.58,
      "first_seen": "14:55",
      "last_seen": "22:59",
      "appearances": 7,
      "last_price": 187500,
      "open": 178500,
      "high": 192400,
      "low": 178500
    },
    "020150": {
      "ticker": "020150",
      "name": "롯데에너지머티리얼즈",
      "max_trade_amount": 52975170900,
      "max_change_pct": 8.29,
      "min_change_pct": 7.68,
      "first_seen": "14:55",
      "last_seen": "22:59",
      "appearances": 7,
      "last_price": 52900,
      "open": 49200,
      "high": 54500,
      "low": 48450
    },
    "295310": {
      "ticker": "295310",
      "name": "에이치브이엠",
      "max_trade_amount": 53001361500,
      "max_change_pct": 10.19,
      "min_change_pct": 9.75,
      "first_seen": "15:15",
      "last_seen": "22:59",
      "appearances": 6,
      "last_price": 99500,
      "open": 94300,
      "high": 102000,
      "low": 93000
    },
    "483650": {
      "ticker": "483650",
      "name": "달바글로벌",
      "max_trade_amount": 51890060800,
      "max_change_pct": 4.82,
      "min_change_pct": 4.72,
      "first_seen": "15:15",
      "last_seen": "22:59",
      "appearances": 6,
      "last_price": 197800,
      "open": 190500,
      "high": 199300,
      "low": 190200
    },
    "049480": {
      "ticker": "049480",
      "name": "오픈베이스",
      "max_trade_amount": 50437912500,
      "max_change_pct": -0.16,
      "min_change_pct": -0.32,
      "first_seen": "15:15",
      "last_seen": "22:59",
      "appearances": 6,
      "last_price": 3125,
      "open": 3200,
      "high": 3520,
      "low": 3100
    },
    "327260": {
      "ticker": "327260",
      "name": "RF머트리얼즈",
      "max_trade_amount": 49896563500,
      "max_change_pct": 4.89,
      "min_change_pct": 3.85,
      "first_seen": "15:15",
      "last_seen": "22:59",
      "appearances": 6,
      "last_price": 100900,
      "open": 98500,
      "high": 109500,
      "low": 97300
    },
    "054540": {
      "ticker": "054540",
      "name": "삼영엠텍",
      "max_trade_amount": 48618746000,
      "max_change_pct": 9.92,
      "min_change_pct": 9.92,
      "first_seen": "18:50",
      "last_seen": "22:59",
      "appearances": 4,
      "last_price": 12850,
      "open": 11740,
      "high": 14200,
      "low": 11520
    }
  },
  "last_snapshot_at": "2026-04-17T22:59:10+09:00",
  "latest_stocks": [
    {
      "ticker": "100790",
      "name": "미래에셋벤처투자",
      "price": 46300,
      "open": 39900,
      "high": 48550,
      "low": 38000,
      "change": 7600,
      "change_pct": 19.64,
      "volume": 21858390,
      "trade_amount": 1012043457000,
      "rank": 1
    },
    {
      "ticker": "046970",
      "name": "우리로",
      "price": 12970,
      "open": 12000,
      "high": 16200,
      "low": 10210,
      "change": -1230,
      "change_pct": -8.66,
      "volume": 52489685,
      "trade_amount": 680791214450,
      "rank": 2
    },
    {
      "ticker": "027360",
      "name": "아주IB투자",
      "price": 11930,
      "open": 11130,
      "high": 13080,
      "low": 10770,
      "change": 960,
      "change_pct": 8.75,
      "volume": 40311238,
      "trade_amount": 480913069340,
      "rank": 3
    },
    {
      "ticker": "098460",
      "name": "고영",
      "price": 33000,
      "open": 29900,
      "high": 34800,
      "low": 29350,
      "change": 3400,
      "change_pct": 11.49,
      "volume": 13445138,
      "trade_amount": 443689554000,
      "rank": 4
    },
    {
      "ticker": "093370",
      "name": "후성",
      "price": 13820,
      "open": 12950,
      "high": 14430,
      "low": 12060,
      "change": 2520,
      "change_pct": 22.3,
      "volume": 31327210,
      "trade_amount": 432942042200,
      "rank": 5
    },
    {
      "ticker": "010820",
      "name": "퍼스텍",
      "price": 13480,
      "open": 11840,
      "high": 14330,
      "low": 11690,
      "change": 1750,
      "change_pct": 14.92,
      "volume": 26713797,
      "trade_amount": 360101983560,
      "rank": 6
    },
    {
      "ticker": "082740",
      "name": "한화엔진",
      "price": 56100,
      "open": 48700,
      "high": 59900,
      "low": 47200,
      "change": 7900,
      "change_pct": 16.39,
      "volume": 5143586,
      "trade_amount": 288555174600,
      "rank": 7
    },
    {
      "ticker": "319400",
      "name": "현대무벡스",
      "price": 32400,
      "open": 32500,
      "high": 34450,
      "low": 31650,
      "change": 1450,
      "change_pct": 4.68,
      "volume": 6051913,
      "trade_amount": 196081981200,
      "rank": 8
    },
    {
      "ticker": "115500",
      "name": "케이씨에스",
      "price": 17780,
      "open": 18470,
      "high": 20300,
      "low": 16010,
      "change": 0,
      "change_pct": 0.0,
      "volume": 10701773,
      "trade_amount": 190277523940,
      "rank": 9
    },
    {
      "ticker": "077970",
      "name": "STX엔진",
      "price": 44000,
      "open": 34200,
      "high": 44000,
      "low": 33600,
      "change": 10150,
      "change_pct": 29.99,
      "volume": 3620387,
      "trade_amount": 159297028000,
      "rank": 10
    },
    {
      "ticker": "457190",
      "name": "이수스페셜티케미컬",
      "price": 111500,
      "open": 105500,
      "high": 118800,
      "low": 103300,
      "change": 8300,
      "change_pct": 8.04,
      "volume": 1426216,
      "trade_amount": 159023084000,
      "rank": 11
    },
    {
      "ticker": "062040",
      "name": "산일전기",
      "price": 198100,
      "open": 189000,
      "high": 202500,
      "low": 188300,
      "change": 9100,
      "change_pct": 4.81,
      "volume": 709909,
      "trade_amount": 140632972900,
      "rank": 12
    },
    {
      "ticker": "009580",
      "name": "무림P&P",
      "price": 3630,
      "open": 3800,
      "high": 4400,
      "low": 3310,
      "change": -80,
      "change_pct": -2.16,
      "volume": 34031500,
      "trade_amount": 123534345000,
      "rank": 13
    },
    {
      "ticker": "071970",
      "name": "HD현대마린엔진",
      "price": 91200,
      "open": 86200,
      "high": 98100,
      "low": 83200,
      "change": 5700,
      "change_pct": 6.67,
      "volume": 1340538,
      "trade_amount": 122257065600,
      "rank": 14
    },
    {
      "ticker": "018880",
      "name": "한온시스템",
      "price": 4160,
      "open": 4105,
      "high": 4370,
      "low": 4090,
      "change": 75,
      "change_pct": 1.84,
      "volume": 25988073,
      "trade_amount": 108110383680,
      "rank": 15
    },
    {
      "ticker": "131760",
      "name": "파인텍",
      "price": 1210,
      "open": 1400,
      "high": 1400,
      "low": 1078,
      "change": 133,
      "change_pct": 12.35,
      "volume": 88262546,
      "trade_amount": 106797680660,
      "rank": 16
    },
    {
      "ticker": "209640",
      "name": "와이제이링크",
      "price": 5920,
      "open": 4610,
      "high": 5920,
      "low": 4600,
      "change": 1360,
      "change_pct": 29.82,
      "volume": 17813819,
      "trade_amount": 105457808480,
      "rank": 17
    },
    {
      "ticker": "067310",
      "name": "하나마이크론",
      "price": 36050,
      "open": 34600,
      "high": 37000,
      "low": 34100,
      "change": 1400,
      "change_pct": 4.04,
      "volume": 2814842,
      "trade_amount": 101475054100,
      "rank": 18
    },
    {
      "ticker": "077360",
      "name": "덕산하이메탈",
      "price": 16530,
      "open": 16900,
      "high": 17650,
      "low": 16100,
      "change": 120,
      "change_pct": 0.73,
      "volume": 6031650,
      "trade_amount": 99703174500,
      "rank": 19
    },
    {
      "ticker": "036170",
      "name": "에이치엠넥스",
      "price": 7700,
      "open": 6680,
      "high": 8170,
      "low": 6620,
      "change": 1300,
      "change_pct": 20.31,
      "volume": 12529177,
      "trade_amount": 96474662900,
      "rank": 20
    },
    {
      "ticker": "321260",
      "name": "프로이천",
      "price": 3030,
      "open": 2850,
      "high": 3670,
      "low": 2770,
      "change": 205,
      "change_pct": 7.26,
      "volume": 31613440,
      "trade_amount": 95788723200,
      "rank": 21
    },
    {
      "ticker": "097230",
      "name": "HJ중공업",
      "price": 28550,
      "open": 27550,
      "high": 28900,
      "low": 26750,
      "change": 1050,
      "change_pct": 3.82,
      "volume": 3350442,
      "trade_amount": 95655119100,
      "rank": 22
    },
    {
      "ticker": "084650",
      "name": "랩지노믹스",
      "price": 1803,
      "open": 1666,
      "high": 1970,
      "low": 1551,
      "change": 280,
      "change_pct": 18.38,
      "volume": 47034223,
      "trade_amount": 84802704069,
      "rank": 23
    },
    {
      "ticker": "065450",
      "name": "빅텍",
      "price": 6150,
      "open": 5510,
      "high": 6540,
      "low": 5460,
      "change": 690,
      "change_pct": 12.64,
      "volume": 13703489,
      "trade_amount": 84276457350,
      "rank": 24
    },
    {
      "ticker": "293580",
      "name": "나우IB",
      "price": 2515,
      "open": 2350,
      "high": 2920,
      "low": 2150,
      "change": 75,
      "change_pct": 3.07,
      "volume": 33439607,
      "trade_amount": 84100611605,
      "rank": 25
    },
    {
      "ticker": "253840",
      "name": "수젠텍",
      "price": 6760,
      "open": 5800,
      "high": 6760,
      "low": 5640,
      "change": 1560,
      "change_pct": 30.0,
      "volume": 12253668,
      "trade_amount": 82834795680,
      "rank": 26
    },
    {
      "ticker": "090460",
      "name": "비에이치",
      "price": 31400,
      "open": 28250,
      "high": 32150,
      "low": 27250,
      "change": 2200,
      "change_pct": 7.53,
      "volume": 2625597,
      "trade_amount": 82443745800,
      "rank": 27
    },
    {
      "ticker": "019170",
      "name": "신풍제약",
      "price": 14090,
      "open": 13100,
      "high": 14400,
      "low": 12870,
      "change": 2950,
      "change_pct": 26.48,
      "volume": 5739779,
      "trade_amount": 80873486110,
      "rank": 28
    },
    {
      "ticker": "131970",
      "name": "두산테스나",
      "price": 111800,
      "open": 100600,
      "high": 112800,
      "low": 99600,
      "change": 11300,
      "change_pct": 11.24,
      "volume": 684374,
      "trade_amount": 76513013200,
      "rank": 29
    },
    {
      "ticker": "332570",
      "name": "PS일렉트로닉스",
      "price": 7290,
      "open": 6810,
      "high": 7440,
      "low": 6690,
      "change": 500,
      "change_pct": 7.36,
      "volume": 10368906,
      "trade_amount": 75589324740,
      "rank": 30
    }
  ],
  "daily_top": [
    {
      "ticker": "100790",
      "name": "미래에셋벤처투자",
      "max_trade_amount": 1012043457000,
      "max_change_pct": 23.77,
      "min_change_pct": 16.8,
      "first_seen": "09:26",
      "last_seen": "22:59",
      "appearances": 18,
      "last_price": 46300,
      "open": 39900,
      "high": 48550,
      "low": 38000
    },
    {
      "ticker": "046970",
      "name": "우리로",
      "max_trade_amount": 680791214450,
      "max_change_pct": -6.69,
      "min_change_pct": -12.89,
      "first_seen": "11:56",
      "last_seen": "22:59",
      "appearances": 11,
      "last_price": 12970,
      "open": 12000,
      "high": 16200,
      "low": 10210
    },
    {
      "ticker": "027360",
      "name": "아주IB투자",
      "max_trade_amount": 480913069340,
      "max_change_pct": 16.13,
      "min_change_pct": 8.75,
      "first_seen": "09:48",
      "last_seen": "22:59",
      "appearances": 17,
      "last_price": 11930,
      "open": 11130,
      "high": 13080,
      "low": 10770
    },
    {
      "ticker": "098460",
      "name": "고영",
      "max_trade_amount": 443689554000,
      "max_change_pct": 12.5,
      "min_change_pct": 2.96,
      "first_seen": "10:11",
      "last_seen": "22:59",
      "appearances": 15,
      "last_price": 33000,
      "open": 29900,
      "high": 34800,
      "low": 29350
    },
    {
      "ticker": "093370",
      "name": "후성",
      "max_trade_amount": 432942042200,
      "max_change_pct": 24.6,
      "min_change_pct": 14.16,
      "first_seen": "09:48",
      "last_seen": "22:59",
      "appearances": 17,
      "last_price": 13820,
      "open": 12950,
      "high": 14430,
      "low": 12060
    },
    {
      "ticker": "010820",
      "name": "퍼스텍",
      "max_trade_amount": 360101983560,
      "max_change_pct": 16.71,
      "min_change_pct": 9.38,
      "first_seen": "09:48",
      "last_seen": "22:59",
      "appearances": 17,
      "last_price": 13480,
      "open": 11840,
      "high": 14330,
      "low": 11690
    },
    {
      "ticker": "082740",
      "name": "한화엔진",
      "max_trade_amount": 288555174600,
      "max_change_pct": 20.54,
      "min_change_pct": 16.39,
      "first_seen": "14:11",
      "last_seen": "22:59",
      "appearances": 10,
      "last_price": 56100,
      "open": 48700,
      "high": 59900,
      "low": 47200
    },
    {
      "ticker": "319400",
      "name": "현대무벡스",
      "max_trade_amount": 196081981200,
      "max_change_pct": 9.53,
      "min_change_pct": 2.91,
      "first_seen": "09:15",
      "last_seen": "22:59",
      "appearances": 19,
      "last_price": 32400,
      "open": 32500,
      "high": 34450,
      "low": 31650
    },
    {
      "ticker": "115500",
      "name": "케이씨에스",
      "max_trade_amount": 190277523940,
      "max_change_pct": 5.51,
      "min_change_pct": -3.94,
      "first_seen": "09:15",
      "last_seen": "22:59",
      "appearances": 19,
      "last_price": 17780,
      "open": 18470,
      "high": 20300,
      "low": 16010
    },
    {
      "ticker": "077970",
      "name": "STX엔진",
      "max_trade_amount": 159297028000,
      "max_change_pct": 29.99,
      "min_change_pct": 29.54,
      "first_seen": "14:11",
      "last_seen": "22:59",
      "appearances": 10,
      "last_price": 44000,
      "open": 34200,
      "high": 44000,
      "low": 33600
    },
    {
      "ticker": "457190",
      "name": "이수스페셜티케미컬",
      "max_trade_amount": 159023084000,
      "max_change_pct": 12.89,
      "min_change_pct": 7.27,
      "first_seen": "09:48",
      "last_seen": "22:59",
      "appearances": 17,
      "last_price": 111500,
      "open": 105500,
      "high": 118800,
      "low": 103300
    },
    {
      "ticker": "062040",
      "name": "산일전기",
      "max_trade_amount": 140632972900,
      "max_change_pct": 5.4,
      "min_change_pct": 4.02,
      "first_seen": "10:24",
      "last_seen": "22:59",
      "appearances": 14,
      "last_price": 198100,
      "open": 189000,
      "high": 202500,
      "low": 188300
    },
    {
      "ticker": "009580",
      "name": "무림P&P",
      "max_trade_amount": 123534345000,
      "max_change_pct": 4.18,
      "min_change_pct": -6.47,
      "first_seen": "09:48",
      "last_seen": "22:59",
      "appearances": 17,
      "last_price": 3630,
      "open": 3800,
      "high": 4400,
      "low": 3310
    },
    {
      "ticker": "071970",
      "name": "HD현대마린엔진",
      "max_trade_amount": 122257065600,
      "max_change_pct": 12.4,
      "min_change_pct": 6.67,
      "first_seen": "14:24",
      "last_seen": "22:59",
      "appearances": 9,
      "last_price": 91200,
      "open": 86200,
      "high": 98100,
      "low": 83200
    },
    {
      "ticker": "018880",
      "name": "한온시스템",
      "max_trade_amount": 108110383680,
      "max_change_pct": 2.94,
      "min_change_pct": 0.98,
      "first_seen": "09:26",
      "last_seen": "22:59",
      "appearances": 18,
      "last_price": 4160,
      "open": 4105,
      "high": 4370,
      "low": 4090
    },
    {
      "ticker": "131760",
      "name": "파인텍",
      "max_trade_amount": 106797680660,
      "max_change_pct": 21.63,
      "min_change_pct": 9.47,
      "first_seen": "10:11",
      "last_seen": "22:59",
      "appearances": 15,
      "last_price": 1210,
      "open": 1400,
      "high": 1400,
      "low": 1078
    },
    {
      "ticker": "209640",
      "name": "와이제이링크",
      "max_trade_amount": 105457808480,
      "max_change_pct": 29.82,
      "min_change_pct": 24.78,
      "first_seen": "10:49",
      "last_seen": "22:59",
      "appearances": 12,
      "last_price": 5920,
      "open": 4610,
      "high": 5920,
      "low": 4600
    },
    {
      "ticker": "067310",
      "name": "하나마이크론",
      "max_trade_amount": 101475054100,
      "max_change_pct": 6.49,
      "min_change_pct": 4.04,
      "first_seen": "11:56",
      "last_seen": "22:59",
      "appearances": 11,
      "last_price": 36050,
      "open": 34600,
      "high": 37000,
      "low": 34100
    },
    {
      "ticker": "077360",
      "name": "덕산하이메탈",
      "max_trade_amount": 99703174500,
      "max_change_pct": 2.44,
      "min_change_pct": -1.28,
      "first_seen": "09:15",
      "last_seen": "22:59",
      "appearances": 19,
      "last_price": 16530,
      "open": 16900,
      "high": 17650,
      "low": 16100
    },
    {
      "ticker": "036170",
      "name": "에이치엠넥스",
      "max_trade_amount": 96474662900,
      "max_change_pct": 25.0,
      "min_change_pct": 12.97,
      "first_seen": "09:48",
      "last_seen": "22:59",
      "appearances": 17,
      "last_price": 7700,
      "open": 6680,
      "high": 8170,
      "low": 6620
    },
    {
      "ticker": "321260",
      "name": "프로이천",
      "max_trade_amount": 95788723200,
      "max_change_pct": 25.13,
      "min_change_pct": 6.9,
      "first_seen": "10:11",
      "last_seen": "22:59",
      "appearances": 15,
      "last_price": 3030,
      "open": 2850,
      "high": 3670,
      "low": 2770
    },
    {
      "ticker": "097230",
      "name": "HJ중공업",
      "max_trade_amount": 95655119100,
      "max_change_pct": 4.0,
      "min_change_pct": 3.64,
      "first_seen": "14:39",
      "last_seen": "22:59",
      "appearances": 8,
      "last_price": 28550,
      "open": 27550,
      "high": 28900,
      "low": 26750
    },
    {
      "ticker": "084650",
      "name": "랩지노믹스",
      "max_trade_amount": 84802704069,
      "max_change_pct": 21.27,
      "min_change_pct": 12.74,
      "first_seen": "09:59",
      "last_seen": "22:59",
      "appearances": 16,
      "last_price": 1803,
      "open": 1666,
      "high": 1970,
      "low": 1551
    },
    {
      "ticker": "065450",
      "name": "빅텍",
      "max_trade_amount": 84276457350,
      "max_change_pct": 16.3,
      "min_change_pct": 11.9,
      "first_seen": "10:35",
      "last_seen": "22:59",
      "appearances": 13,
      "last_price": 6150,
      "open": 5510,
      "high": 6540,
      "low": 5460
    },
    {
      "ticker": "293580",
      "name": "나우IB",
      "max_trade_amount": 84100611605,
      "max_change_pct": 6.35,
      "min_change_pct": 0.0,
      "first_seen": "10:24",
      "last_seen": "22:59",
      "appearances": 14,
      "last_price": 2515,
      "open": 2350,
      "high": 2920,
      "low": 2150
    },
    {
      "ticker": "253840",
      "name": "수젠텍",
      "max_trade_amount": 82834795680,
      "max_change_pct": 30.0,
      "min_change_pct": 21.73,
      "first_seen": "09:48",
      "last_seen": "22:59",
      "appearances": 17,
      "last_price": 6760,
      "open": 5800,
      "high": 6760,
      "low": 5640
    },
    {
      "ticker": "090460",
      "name": "비에이치",
      "max_trade_amount": 82443745800,
      "max_change_pct": 9.93,
      "min_change_pct": 5.65,
      "first_seen": "14:11",
      "last_seen": "22:59",
      "appearances": 10,
      "last_price": 31400,
      "open": 28250,
      "high": 32150,
      "low": 27250
    },
    {
      "ticker": "019170",
      "name": "신풍제약",
      "max_trade_amount": 80873486110,
      "max_change_pct": 26.48,
      "min_change_pct": 18.4,
      "first_seen": "11:56",
      "last_seen": "22:59",
      "appearances": 11,
      "last_price": 14090,
      "open": 13100,
      "high": 14400,
      "low": 12870
    },
    {
      "ticker": "131970",
      "name": "두산테스나",
      "max_trade_amount": 76513013200,
      "max_change_pct": 11.34,
      "min_change_pct": 10.45,
      "first_seen": "14:11",
      "last_seen": "22:59",
      "appearances": 10,
      "last_price": 111800,
      "open": 100600,
      "high": 112800,
      "low": 99600
    },
    {
      "ticker": "332570",
      "name": "PS일렉트로닉스",
      "max_trade_amount": 75589324740,
      "max_change_pct": 7.36,
      "min_change_pct": 6.33,
      "first_seen": "14:11",
      "last_seen": "22:59",
      "appearances": 10,
      "last_price": 7290,
      "open": 6810,
      "high": 7440,
      "low": 6690
    },
    {
      "ticker": "038060",
      "name": "루멘스",
      "max_trade_amount": 72960481227,
      "max_change_pct": 5.04,
      "min_change_pct": -7.1,
      "first_seen": "14:11",
      "last_seen": "22:59",
      "appearances": 10,
      "last_price": 1531,
      "open": 1647,
      "high": 2100,
      "low": 1153
    },
    {
      "ticker": "096530",
      "name": "씨젠",
      "max_trade_amount": 68839676500,
      "max_change_pct": 9.84,
      "min_change_pct": 7.83,
      "first_seen": "10:24",
      "last_seen": "22:59",
      "appearances": 14,
      "last_price": 27350,
      "open": 28050,
      "high": 29300,
      "low": 26300
    },
    {
      "ticker": "017550",
      "name": "수산세보틱스",
      "max_trade_amount": 60764791280,
      "max_change_pct": 8.6,
      "min_change_pct": 6.94,
      "first_seen": "14:11",
      "last_seen": "22:59",
      "appearances": 10,
      "last_price": 3280,
      "open": 3015,
      "high": 3570,
      "low": 2950
    },
    {
      "ticker": "440110",
      "name": "파두",
      "max_trade_amount": 57908146000,
      "max_change_pct": 2.43,
      "min_change_pct": 2.08,
      "first_seen": "14:11",
      "last_seen": "22:59",
      "appearances": 10,
      "last_price": 59000,
      "open": 57800,
      "high": 62500,
      "low": 56400
    },
    {
      "ticker": "388210",
      "name": "씨엠티엑스",
      "max_trade_amount": 57770537500,
      "max_change_pct": 7.04,
      "min_change_pct": 6.45,
      "first_seen": "14:11",
      "last_seen": "22:59",
      "appearances": 10,
      "last_price": 162500,
      "open": 150600,
      "high": 164500,
      "low": 149500
    },
    {
      "ticker": "089970",
      "name": "브이엠",
      "max_trade_amount": 56083975800,
      "max_change_pct": 9.76,
      "min_change_pct": 9.36,
      "first_seen": "14:55",
      "last_seen": "22:59",
      "appearances": 7,
      "last_price": 55100,
      "open": 49800,
      "high": 56100,
      "low": 49500
    },
    {
      "ticker": "150900",
      "name": "파수",
      "max_trade_amount": 55574764300,
      "max_change_pct": 4.77,
      "min_change_pct": 0.2,
      "first_seen": "14:11",
      "last_seen": "22:59",
      "appearances": 10,
      "last_price": 5060,
      "open": 4950,
      "high": 6220,
      "low": 4410
    },
    {
      "ticker": "080580",
      "name": "오킨스전자",
      "max_trade_amount": 54110027800,
      "max_change_pct": 11.89,
      "min_change_pct": 10.35,
      "first_seen": "14:39",
      "last_seen": "22:59",
      "appearances": 8,
      "last_price": 25100,
      "open": 22700,
      "high": 26300,
      "low": 22400
    },
    {
      "ticker": "295310",
      "name": "에이치브이엠",
      "max_trade_amount": 53001361500,
      "max_change_pct": 10.19,
      "min_change_pct": 9.75,
      "first_seen": "15:15",
      "last_seen": "22:59",
      "appearances": 6,
      "last_price": 99500,
      "open": 94300,
      "high": 102000,
      "low": 93000
    },
    {
      "ticker": "020150",
      "name": "롯데에너지머티리얼즈",
      "max_trade_amount": 52975170900,
      "max_change_pct": 8.29,
      "min_change_pct": 7.68,
      "first_seen": "14:55",
      "last_seen": "22:59",
      "appearances": 7,
      "last_price": 52900,
      "open": 49200,
      "high": 54500,
      "low": 48450
    },
    {
      "ticker": "417010",
      "name": "나노팀",
      "max_trade_amount": 52754762010,
      "max_change_pct": 15.19,
      "min_change_pct": 14.8,
      "first_seen": "14:55",
      "last_seen": "22:59",
      "appearances": 7,
      "last_price": 12030,
      "open": 10480,
      "high": 12620,
      "low": 10480
    },
    {
      "ticker": "099320",
      "name": "쎄트렉아이",
      "max_trade_amount": 52404562500,
      "max_change_pct": 7.7,
      "min_change_pct": 7.58,
      "first_seen": "14:55",
      "last_seen": "22:59",
      "appearances": 7,
      "last_price": 187500,
      "open": 178500,
      "high": 192400,
      "low": 178500
    },
    {
      "ticker": "483650",
      "name": "달바글로벌",
      "max_trade_amount": 51890060800,
      "max_change_pct": 4.82,
      "min_change_pct": 4.72,
      "first_seen": "15:15",
      "last_seen": "22:59",
      "appearances": 6,
      "last_price": 197800,
      "open": 190500,
      "high": 199300,
      "low": 190200
    },
    {
      "ticker": "049480",
      "name": "오픈베이스",
      "max_trade_amount": 50437912500,
      "max_change_pct": -0.16,
      "min_change_pct": -0.32,
      "first_seen": "15:15",
      "last_seen": "22:59",
      "appearances": 6,
      "last_price": 3125,
      "open": 3200,
      "high": 3520,
      "low": 3100
    },
    {
      "ticker": "327260",
      "name": "RF머트리얼즈",
      "max_trade_amount": 49896563500,
      "max_change_pct": 4.89,
      "min_change_pct": 3.85,
      "first_seen": "15:15",
      "last_seen": "22:59",
      "appearances": 6,
      "last_price": 100900,
      "open": 98500,
      "high": 109500,
      "low": 97300
    },
    {
      "ticker": "054540",
      "name": "삼영엠텍",
      "max_trade_amount": 48618746000,
      "max_change_pct": 9.92,
      "min_change_pct": 9.92,
      "first_seen": "18:50",
      "last_seen": "22:59",
      "appearances": 4,
      "last_price": 12850,
      "open": 11740,
      "high": 14200,
      "low": 11520
    }
  ]
}