{"KOSPI":{"name":"코스피","value":7150.26,"prev_close":6747.95,"change_pct":5.96,"candles_10m":[{"t":"0900","o":7052.09,"h":7140.31,"l":7052.09,"c":7118.35},{"t":"0910","o":7115.76,"h":7153.42,"l":7101.29,"c":7150.26}],"range_240d":{"high":9385.59,"low":3079.27,"days":240},"trade_date":"2026-07-22","asof":"2026-07-22T09:15:04+09:00","session":"intraday"},"KOSDAQ":{"name":"코스닥","value":787.16,"prev_close":753.34,"change_pct":4.49,"candles_10m":[{"t":"0900","o":772.41,"h":787.43,"l":772.07,"c":786.78},{"t":"0910","o":786.69,"h":789.23,"l":785.62,"c":787.16}],"range_240d":{"high":1229.42,"low":730.81,"days":240},"trade_date":"2026-07-22","asof":"2026-07-22T09:15:04+09:00","session":"intraday"},"as_of":"2026-07-22T09:15:04+09:00"}
